upbit/__init__.py
upbit/upbit.py
upbit/upbit_websocket.py
upbit_wrapper/__init__.py
upbit_wrapper/upbit.py
upbit_wrapper/upbit_websocket.py
upbit_wrapper/upbit_wrapper.py
upbit_wrapper-0.0.1.dist-info/LICENSE
upbit_wrapper-0.0.1.dist-info/METADATA
upbit_wrapper-0.0.1.dist-info/WHEEL
upbit_wrapper-0.0.1.dist-info/top_level.txt
upbit_wrapper-0.0.1.dist-info/RECORD
